ipfsclient/__init__.py
ipfsclient/ipfs.py
ipfsclient-0.1.0.dist-info/LICENSE
ipfsclient-0.1.0.dist-info/METADATA
ipfsclient-0.1.0.dist-info/WHEEL
ipfsclient-0.1.0.dist-info/top_level.txt
ipfsclient-0.1.0.dist-info/RECORD
