Metadata-Version: 2.1
Name: ipfsclient
Version: 0.1.0
Summary: IPFS RPC Client
Home-page: https://github.com/nanoswap/ipfsclient
Author: Nathaniel Schultz
Author-email: nate@nanoswap.finance
Project-URL: Bug Tracker, https://github.com/nanoswap/ipfsclient/issues
Classifier: Programming Language :: Python :: 3
Classifier: License :: OSI Approved :: The Unlicense (Unlicense)
Requires-Python: >=3.11
License-File: LICENSE
